adafruit_apds9960/__init__.py
adafruit_apds9960/apds9960.py
adafruit_apds9960/colorutility.py
adafruit_circuitpython_apds9960-3.1.15.dist-info/licenses/LICENSE
adafruit_circuitpython_apds9960-3.1.15.dist-info/METADATA
adafruit_circuitpython_apds9960-3.1.15.dist-info/WHEEL
adafruit_circuitpython_apds9960-3.1.15.dist-info/top_level.txt
adafruit_circuitpython_apds9960-3.1.15.dist-info/RECORD
